[{"ImagePath": "https://schale.gg/images/student/collection/10036.webp", "MessageJP": "ヒナタ", "MessageTW": "日向", "MessageEN": "Hinata"}, {"MessageId": 100350420, "Flag": 2, "Type": 4, "NextId": 100360420, "MessageType": "Text", "ImagePath": "", "MessageJP": "既読", "MessageTW": "已讀", "MessageEN": "Message read"}, {"MessageId": 100360420, "Flag": 2, "Type": 0, "NextId": 100360430, "MessageType": "Text", "ImagePath": "", "MessageJP": "あの……", "MessageTW": "那個……", "MessageEN": "Sensei..."}, {"MessageId": 100360430, "Flag": 1, "Type": 0, "NextId": 100360440, "MessageType": "Text", "ImagePath": "", "MessageJP": "先生、今よろしいでしょうか？", "MessageTW": "老師，現在方便打擾一下嗎？", "MessageEN": "So..."}, {"MessageId": 100360440, "Flag": 2, "Type": 3, "NextId": 100360450, "MessageType": "Text", "ImagePath": "", "MessageJP": "どうしたの、ヒナタ？", "MessageTW": "怎麼了嗎，日向？", "MessageEN": "Hinata?"}, {"MessageId": 100360440, "Flag": 2, "Type": 3, "NextId": 100360450, "MessageType": "Text", "ImagePath": "", "MessageJP": "うん、大丈夫だよ", "MessageTW": "嗯，可以唷", "MessageEN": "Is something the matter?"}, {"MessageId": 100360450, "Flag": 2, "Type": 0, "NextId": 100360460, "MessageType": "Text", "ImagePath": "", "MessageJP": "そのですね", "MessageTW": "那個", "MessageEN": "Ah"}, {"MessageId": 100360460, "Flag": 1, "Type": 0, "NextId": 100360461, "MessageType": "Text", "ImagePath": "", "MessageJP": "一応、あらためてお聞きしておきたくて……", "MessageTW": "想再向您請教一下……", "MessageEN": "Nothing really, just..."}, {"MessageId": 100360461, "Flag": 2, "Type": 0, "NextId": 100360470, "MessageType": "Text", "ImagePath": "", "MessageJP": "先日のピクニックに持っていったお弁当、いかがでしたか……？", "MessageTW": "我上次帶去野餐的便當，您覺得如何呢……？", "MessageEN": "How did you like the boxed lunch last time?"}, {"MessageId": 100360470, "Flag": 1, "Type": 0, "NextId": 100360480, "MessageType": "Text", "ImagePath": "", "MessageJP": "お気に召していただけてたら良かったのですが……", "MessageTW": "要是有符合您的喜好就好了……", "MessageEN": "I hope it was okay..."}, {"MessageId": 100360480, "Flag": 2, "Type": 3, "NextId": 100360490, "MessageType": "Text", "ImagePath": "", "MessageJP": "もちろん、すごくおいしかったよ", "MessageTW": "當然，非常好吃唷", "MessageEN": "It was more than okay. I'd love to have more."}, {"MessageId": 100360480, "Flag": 2, "Type": 3, "NextId": 100360490, "MessageType": "Text", "ImagePath": "", "MessageJP": "また作ってくれるとうれしいな", "MessageTW": "要是能再做給我吃，我會很開心的", "MessageEN": "Why? Are you actually going to make me another one?"}, {"MessageId": 100360490, "Flag": 2, "Type": 0, "NextId": 100360491, "MessageType": "Text", "ImagePath": "", "MessageJP": "ほ", "MessageTW": "真", "MessageEN": "Ah"}, {"MessageId": 100360491, "Flag": 2, "Type": 0, "NextId": 100360500, "MessageType": "Text", "ImagePath": "", "MessageJP": "本当ですか？", "MessageTW": "真的嗎？", "MessageEN": "Is it okay to?"}, {"MessageId": 100360500, "Flag": 1, "Type": 0, "NextId": 100350510, "MessageType": "Text", "ImagePath": "", "MessageJP": "ありがとうございます！", "MessageTW": "非常感謝！", "MessageEN": "Thank you!"}, {"MessageId": 100350510, "Flag": 2, "Type": 2, "NextId": 100360510, "MessageType": "Text", "ImagePath": "", "MessageJP": "ヒナタの絆イベントへ", "MessageTW": "前往日向的羈絆劇情", "MessageEN": "Go to Hinata's Event"}, {"MessageId": 100360510, "Flag": 2, "Type": 0, "NextId": 100360520, "MessageType": "Text", "ImagePath": "", "MessageJP": "あっ", "MessageTW": "那", "MessageEN": "Umm..."}, {"MessageId": 100360520, "Flag": 1, "Type": 0, "NextId": 100360530, "MessageType": "Text", "ImagePath": "", "MessageJP": "あの", "MessageTW": "那個", "MessageEN": "So..."}, {"MessageId": 100360530, "Flag": 1, "Type": 0, "NextId": 100360531, "MessageType": "Text", "ImagePath": "", "MessageJP": "先生！", "MessageTW": "老師！", "MessageEN": "Sen"}, {"MessageId": 100360531, "Flag": 2, "Type": 0, "NextId": 100360540, "MessageType": "Text", "ImagePath": "", "MessageJP": "何度も本当にすみません……", "MessageTW": "一直打擾您真的非常抱歉……", "MessageEN": "Sensei!"}, {"MessageId": 100360540, "Flag": 1, "Type": 0, "NextId": 100360541, "MessageType": "Text", "ImagePath": "", "MessageJP": "先ほど気づいたのですが……", "MessageTW": "我剛剛才注意到……", "MessageEN": "I'm so sorry, Sensei, I"}, {"MessageId": 100360541, "Flag": 2, "Type": 0, "NextId": 100360550, "MessageType": "Text", "ImagePath": "", "MessageJP": "先生のお弁当箱を台帳と間違えて持って帰ってしまったみたいで……", "MessageTW": "我好像把老師的便當盒和帳本搞混，所以不小心帶回來了……", "MessageEN": "I mixed up the boxed lunch with the management ledger and brought it by mistake again..."}, {"MessageId": 100360550, "Flag": 2, "Type": 3, "NextId": 100360560, "MessageType": "Text", "ImagePath": "", "MessageJP": "あ、本当だ", "MessageTW": "啊，真的呢", "MessageEN": "Alas, I just noticed it myself."}, {"MessageId": 100360550, "Flag": 2, "Type": 3, "NextId": 100360560, "MessageType": "Text", "ImagePath": "", "MessageJP": "確かに重かったかも……それじゃあ、また近いうちにあの公園で", "MessageTW": "那可能會有點重……這樣的話，近期再去那個公園見面吧", "MessageEN": "No wonder it was so heavy. Let's meet there again."}, {"MessageId": 100360560, "Flag": 2, "Type": 0, "NextId": 100360570, "MessageType": "Text", "ImagePath": "", "MessageJP": "あ", "MessageTW": "啊", "MessageEN": "Ah"}, {"MessageId": 100360570, "Flag": 1, "Type": 0, "NextId": 100360580, "MessageType": "Text", "ImagePath": "", "MessageJP": "はいっ！", "MessageTW": "好的！", "MessageEN": "Okay!"}, {"MessageId": 100360580, "Flag": 1, "Type": 0, "NextId": -1, "MessageType": "Text", "ImagePath": "", "MessageJP": "ありがとうございます……", "MessageTW": "非常感謝……", "MessageEN": "Thank you, Sensei..."}]