[
    {
        "CharacterId": 10021,
        "MessageJP": "アズサ（水着）",
        "MessageKR": "아즈사(수영복)",
        "MessageTW": "梓(泳裝)",
        "MessageEN": "Azusa (Swimsuit)"
    },
    {
        "MessageId": 10011440,
        "Flag": 2,
        "Type": 4,
        "NextId": 10021440,
        "MessageType": "Text",
        "ImagePath": "",
        "MessageJP": "既読",
        "MessageKR": "읽혔습니다",
        "MessageTW": "已讀",
        "MessageEN": "Message read"
    },
    {
        "MessageId": 10021440,
        "Flag": 2,
        "Type": 0,
        "NextId": 10021450,
        "MessageType": "Text",
        "ImagePath": "",
        "MessageJP": "先生",
        "MessageKR": "……선생님.",
        "MessageTW": "老師",
        "MessageEN": "Sensei."
    },
    {
        "MessageId": 10021450,
        "Flag": 1,
        "Type": 0,
        "NextId": 10021460,
        "MessageType": "Text",
        "ImagePath": "",
        "MessageJP": "……何かが足りない気がする",
        "MessageKR": "아직이야. 생각해 보니 아직 충분하지 않아.",
        "MessageTW": "……感覺缺少了什麼",
        "MessageEN": "It's not enough, now that I think of it."
    },
    {
        "MessageId": 10021460,
        "Flag": 1,
        "Type": 0,
        "NextId": 10021461,
        "MessageType": "Text",
        "ImagePath": "",
        "MessageJP": "私の戦術的直感がそう告げてるの",
        "MessageKR": "내 전술적 직감이 말해주고 있어.",
        "MessageTW": "我的戰術直覺如此告訴我",
        "MessageEN": "My tactical intuition is telling me."
    },
    {
        "MessageId": 10021461,
        "Flag": 2,
        "Type": 0,
        "NextId": 10021470,
        "MessageType": "Text",
        "ImagePath": "",
        "MessageJP": "きっとまだ、この夏には何かがあるって",
        "MessageKR": "분명 여기엔 뭔가가 더 있다고 말이야.",
        "MessageTW": "這個夏天一定還少了什麼",
        "MessageEN": "That there is something else here."
    },
    {
        "MessageId": 10021470,
        "Flag": 2,
        "Type": 3,
        "NextId": 10021480,
        "MessageType": "Text",
        "ImagePath": "",
        "MessageJP": "戦術的直感……？",
        "MessageKR": "……갑자기 전술적 직감?",
        "MessageTW": "戰術直覺……？",
        "MessageEN": "Tactical intuition? Where's this coming from?"
    },
    {
        "MessageId": 10021470,
        "Flag": 2,
        "Type": 3,
        "NextId": 10021480,
        "MessageType": "Text",
        "ImagePath": "",
        "MessageJP": "何かやり残したことが、ってことかな？",
        "MessageKR": "또 뭔가 하고 싶은 것이 생겼구나.",
        "MessageTW": "有什麼沒做的事嗎？",
        "MessageEN": "I guess you still aren't satisfied, huh?"
    },
    {
        "MessageId": 10021480,
        "Flag": 2,
        "Type": 0,
        "NextId": 10021481,
        "MessageType": "Text",
        "ImagePath": "",
        "MessageJP": "それについて、戦略的な話し合いが必要",
        "MessageKR": "응.",
        "MessageTW": "這部分會需要戰略性的討論",
        "MessageEN": "Yes."
    },
    {
        "MessageId": 10021481,
        "Flag": 2,
        "Type": 0,
        "NextId": 10021490,
        "MessageType": "Text",
        "ImagePath": "",
        "MessageJP": "時間はあまり残されてない",
        "MessageKR": "그래서 그것에 대해, 전략적인 논의가 필요해.",
        "MessageTW": "沒剩多少時間了",
        "MessageEN": "I need to discuss strategy with someone."
    },
    {
        "MessageId": 10021490,
        "Flag": 2,
        "Type": 3,
        "NextId": 10021500,
        "MessageType": "Text",
        "ImagePath": "",
        "MessageJP": "「戦術」と「戦略」ってややこしいよね……",
        "MessageKR": "방금 전엔 '전술적'이라고 했던 거 같은데……",
        "MessageTW": "「戰術」和「戰略」很複雜呢……",
        "MessageEN": "Didn't you just say 'tactical'?"
    },
    {
        "MessageId": 10021500,
        "Flag": 2,
        "Type": 0,
        "NextId": 10021501,
        "MessageType": "Text",
        "ImagePath": "",
        "MessageJP": "とにかく、今から先生のところに行く",
        "MessageKR": "어디로 가면 되지?",
        "MessageTW": "總之，現在過去老師那邊",
        "MessageEN": "Where should I head to?"
    },
    {
        "MessageId": 10021501,
        "Flag": 2,
        "Type": 0,
        "NextId": 10011517,
        "MessageType": "Text",
        "ImagePath": "",
        "MessageJP": "今、どこにいる？",
        "MessageKR": "내가 선생님께 찾아가겠어.",
        "MessageTW": "你現在在哪裡？",
        "MessageEN": "I'll head to where you are."
    },
    {
        "MessageId": 10011517,
        "Flag": 2,
        "Type": 2,
        "NextId": 10021510,
        "MessageType": "Text",
        "ImagePath": "",
        "MessageJP": "アズサ（水着）の絆イベントへ",
        "MessageKR": "아즈사(수영복)의 인연스토리로",
        "MessageTW": "前往梓(泳裝)的羈絆劇情",
        "MessageEN": "Go to Azusa (Swimsuit)'s Event"
    },
    {
        "MessageId": 10021510,
        "Flag": 2,
        "Type": 0,
        "NextId": 10021520,
        "MessageType": "Text",
        "ImagePath": "",
        "MessageJP": "先生、一つ言い忘れてた",
        "MessageKR": "선생님. 말하지 않고 잊은 게 있어.",
        "MessageTW": "老師，忘了說一件事",
        "MessageEN": "There is something I forgot to tell you, Sensei."
    },
    {
        "MessageId": 10021520,
        "Flag": 1,
        "Type": 0,
        "NextId": 10021521,
        "MessageType": "Text",
        "ImagePath": "",
        "MessageJP": "今日のこと、それから今日私が言ったこと",
        "MessageKR": "오늘 있었던 일, 오늘 내가 했던 말들.",
        "MessageTW": "今天的事，還有今天我說的話",
        "MessageEN": "Everything that happened today, whatever I said..."
    },
    {
        "MessageId": 10021521,
        "Flag": 2,
        "Type": 0,
        "NextId": 10021530,
        "MessageType": "Text",
        "ImagePath": "",
        "MessageJP": "全部機密事項だから、誰にも言わないで",
        "MessageKR": "당연한 이야기지만 모두 대외비로 처리해줘.",
        "MessageTW": "全部都是機密事項，不要告訴任何人",
        "MessageEN": "You must keep it a secret from the others."
    },
    {
        "MessageId": 10021530,
        "Flag": 1,
        "Type": 0,
        "NextId": 10021540,
        "MessageType": "Text",
        "ImagePath": "",
        "MessageJP": "分かった？",
        "MessageKR": "알았지?",
        "MessageTW": "明白了嗎？",
        "MessageEN": "Understood?"
    },
    {
        "MessageId": 10021540,
        "Flag": 2,
        "Type": 3,
        "NextId": 10021550,
        "MessageType": "Text",
        "ImagePath": "",
        "MessageJP": "そうなの……？とりあえず、了解",
        "MessageKR": "극비사항인 거야?",
        "MessageTW": "是嗎……？總之了解了",
        "MessageEN": "Is it something confidential now?"
    },
    {
        "MessageId": 10021550,
        "Flag": 2,
        "Type": 0,
        "NextId": 10021551,
        "MessageType": "Text",
        "ImagePath": "",
        "MessageJP": "忘れないで",
        "MessageKR": "당연하지.",
        "MessageTW": "別忘了",
        "MessageEN": "Naturally."
    },
    {
        "MessageId": 10021551,
        "Flag": 2,
        "Type": 0,
        "NextId": 10021560,
        "MessageType": "Text",
        "ImagePath": "",
        "MessageJP": "もしこの秘密が漏れたとしたら、間違いなく犯人は先生だから",
        "MessageKR": "극비사항이야. 새어 나가면 반드시 선생님이 범인이지.",
        "MessageTW": "如果這個秘密洩露出去，犯人肯定是老師",
        "MessageEN": "It's top secret. So if it leaks, I'll know it was you."
    },
    {
        "MessageId": 10021560,
        "Flag": 1,
        "Type": 0,
        "NextId": 10021561,
        "MessageType": "Text",
        "ImagePath": "",
        "MessageJP": "……",
        "MessageKR": "……",
        "MessageTW": "……",
        "MessageEN": "..."
    },
    {
        "MessageId": 10021561,
        "Flag": 2,
        "Type": 0,
        "NextId": -1,
        "MessageType": "Text",
        "ImagePath": "",
        "MessageJP": "先生以外の人に知られたら、困る",
        "MessageKR": "선생님 이외에는, 아무도 본 적 없는 거니까.",
        "MessageTW": "如果被老師以外的人知道，我會很困擾",
        "MessageEN": "That was for only you, Sensei."
    }
]