[
    {
        "CharacterId": 10016,
        "MessageJP": "ミドリ",
        "MessageKR": "미도리",
        "MessageTW": "綠",
        "MessageEN": "Midori"
    },
    {
        "MessageId": 100150010,
        "Flag": 2,
        "Type": 4,
        "NextId": 100160010,
        "MessageType": "Text",
        "ImagePath": "",
        "MessageJP": "既読",
        "MessageKR": "읽혔습니다",
        "MessageTW": "已讀",
        "MessageEN": "Message read"
    },
    {
        "MessageId": 100160010,
        "Flag": 2,
        "Type": 0,
        "NextId": 100160020,
        "MessageType": "Text",
        "ImagePath": "",
        "MessageJP": "先生、今日お時間ありますか？",
        "MessageKR": "선생님, 혹시 시간 있으신가요?",
        "MessageTW": "老師，你今天有時間嗎？",
        "MessageEN": "Do you have a moment, Sensei?"
    },
    {
        "MessageId": 100160020,
        "Flag": 1,
        "Type": 0,
        "NextId": 100160021,
        "MessageType": "Text",
        "ImagePath": "",
        "MessageJP": "実はその、",
        "MessageKR": "그게 다른 게 아니라.",
        "MessageTW": "事實上，那個",
        "MessageEN": "It's just..."
    },
    {
        "MessageId": 100160021,
        "Flag": 2,
        "Type": 0,
        "NextId": 100160030,
        "MessageType": "Text",
        "ImagePath": "",
        "MessageJP": "相談したいことがありまして……",
        "MessageKR": "상담하고 싶은 게 있는데요……",
        "MessageTW": "有想要商量的事情……",
        "MessageEN": "I have something I need to talk to you about..."
    },
    {
        "MessageId": 100160030,
        "Flag": 2,
        "Type": 3,
        "NextId": 100160040,
        "MessageType": "Text",
        "ImagePath": "",
        "MessageJP": "相談したいこと？",
        "MessageKR": "상담?",
        "MessageTW": "想要商量的事情？",
        "MessageEN": "Huh? Talk to me?"
    },
    {
        "MessageId": 100160040,
        "Flag": 2,
        "Type": 0,
        "NextId": 100150057,
        "MessageType": "Text",
        "ImagePath": "",
        "MessageJP": "はい。私は今日ずっと部室にいますので、よろしければお願いします！",
        "MessageKR": "네, 넷! 저희 동아리실에서 기다리고 있을게요!",
        "MessageTW": "是的。我今天都會在社團教室，如果可以的話就麻煩老師了！",
        "MessageEN": "Yeah! I'll be waiting for you in our club room!"
    },
    {
        "MessageId": 100150057,
        "Flag": 2,
        "Type": 2,
        "NextId": 100160050,
        "MessageType": "Text",
        "ImagePath": "",
        "MessageJP": "ミドリの絆イベントへ",
        "MessageKR": "미도리의 인연스토리로",
        "MessageTW": "前往綠的羈絆劇情",
        "MessageEN": "Go to Midori's Event"
    },
    {
        "MessageId": 100160050,
        "Flag": 2,
        "Type": 0,
        "NextId": 100160051,
        "MessageType": "Text",
        "ImagePath": "",
        "MessageJP": "……すみません",
        "MessageKR": "……죄송합니다.",
        "MessageTW": "……對不起",
        "MessageEN": "Sorry..."
    },
    {
        "MessageId": 100160051,
        "Flag": 2,
        "Type": 0,
        "NextId": 100160060,
        "MessageType": "Text",
        "ImagePath": "",
        "MessageJP": "つい熱くなってしまい、先生にご迷惑を……",
        "MessageKR": "괜히 게임으로 열이 오른 탓에 선생님에게 엄청난 민폐를……",
        "MessageTW": "不知不覺就一頭熱，給老師添麻煩了……",
        "MessageEN": "I'm just so obsessed with this game... I didn't realize I was putting you through so much, Sensei..."
    },
    {
        "MessageId": 100160060,
        "Flag": 2,
        "Type": 3,
        "NextId": 100160070,
        "MessageType": "Text",
        "ImagePath": "",
        "MessageJP": "ミドリの新たな一面が明らかに……",
        "MessageKR": "미도리가 가진 의외의 일면을 발견했어……",
        "MessageTW": "發現了綠的另外一面……",
        "MessageEN": "I saw a surprising new side of you, Midori..."
    },
    {
        "MessageId": 100160060,
        "Flag": 2,
        "Type": 3,
        "NextId": 100160070,
        "MessageType": "Text",
        "ImagePath": "",
        "MessageJP": "大丈夫、すごく楽しかったよ",
        "MessageKR": "괜찮아. 무척 재미있었으니까.",
        "MessageTW": "沒關係，我很開心",
        "MessageEN": "It's okay. It was a lot of fun!"
    },
    {
        "MessageId": 100160070,
        "Flag": 2,
        "Type": 0,
        "NextId": 100160071,
        "MessageType": "Text",
        "ImagePath": "",
        "MessageJP": "う、うぅ……穴があったら入りたいです……",
        "MessageKR": "으, 으으…… 쥐구멍이 있다면 숨고 싶어요……",
        "MessageTW": "唔，唔……有洞的話好想鑽進去……",
        "MessageEN": "Agh... I just wanna hide somewhere..."
    },
    {
        "MessageId": 100160071,
        "Flag": 2,
        "Type": 0,
        "NextId": -1,
        "MessageType": "Text",
        "ImagePath": "",
        "MessageJP": "次は対戦型ではないゲームで、お願いします……",
        "MessageKR": "다음번엔 대전 게임이 아닌 쪽으로…… 부탁드릴게요……",
        "MessageTW": "下次會是對戰類型之外的遊戲，再拜託老師了……",
        "MessageEN": "Next time, can we play something that's not so competitive...?"
    }
]