[
    {
        "CharacterId": 10072,
        "MessageJP": "サキ（水着）",
        "MessageKR": "사키(수영복)",
        "MessageTW": "咲希(泳裝)",
        "MessageEN": "Saki (Swimsuit)"
    },
    {
        "MessageId": 100710010,
        "Flag": 2,
        "Type": 4,
        "NextId": 100720010,
        "MessageType": "Text",
        "ImagePath": "",
        "MessageJP": "既読",
        "MessageKR": "읽혔습니다",
        "MessageTW": "已讀",
        "MessageEN": "Message read"
    },
    {
        "MessageId": 100720010,
        "Flag": 2,
        "Type": 0,
        "NextId": 100720020,
        "MessageType": "Text",
        "ImagePath": "",
        "MessageJP": "先生、今何してる？",
        "MessageKR": "선생님, 지금 뭐 하고 있어?",
        "MessageTW": "",
        "MessageEN": ""
    },
    {
        "MessageId": 100720020,
        "Flag": 2,
        "Type": 3,
        "NextId": 100720030,
        "MessageType": "Text",
        "ImagePath": "",
        "MessageJP": "休憩中だよ",
        "MessageKR": "숨 쉬어",
        "MessageTW": "",
        "MessageEN": ""
    },
    {
        "MessageId": 100720020,
        "Flag": 2,
        "Type": 3,
        "NextId": 100720040,
        "MessageType": "Text",
        "ImagePath": "",
        "MessageJP": "呼吸、かな……",
        "MessageKR": "그냥 쉬고 있어",
        "MessageTW": "",
        "MessageEN": ""
    },
    {
        "MessageId": 100720030,
        "Flag": 2,
        "Type": 0,
        "NextId": 100720031,
        "MessageType": "Text",
        "ImagePath": "",
        "MessageJP": "？",
        "MessageKR": "?",
        "MessageTW": "",
        "MessageEN": ""
    },
    {
        "MessageId": 100720031,
        "Flag": 2,
        "Type": 0,
        "NextId": 100720032,
        "MessageType": "Text",
        "ImagePath": "",
        "MessageJP": "なんだそれ",
        "MessageKR": "그게 뭐야.",
        "MessageTW": "",
        "MessageEN": ""
    },
    {
        "MessageId": 100720032,
        "Flag": 2,
        "Type": 0,
        "NextId": 100720040,
        "MessageType": "Text",
        "ImagePath": "",
        "MessageJP": "何もしてないってことか？",
        "MessageKR": "아무것도 안 하고 있다는 뜻이잖아. 장난치지 마.",
        "MessageTW": "",
        "MessageEN": ""
    },
    {
        "MessageId": 100720040,
        "Flag": 1,
        "Type": 0,
        "NextId": 100720050,
        "MessageType": "Text",
        "ImagePath": "",
        "MessageJP": "せっかく海まで来たんだから",
        "MessageKR": "모처럼 바다에 왔는데 시간이 아깝지도 않은 거야?",
        "MessageTW": "",
        "MessageEN": ""
    },
    {
        "MessageId": 100720050,
        "Flag": 1,
        "Type": 0,
        "NextId": 100720060,
        "MessageType": "Text",
        "ImagePath": "",
        "MessageJP": "海でしか出来ないことをしないと、もったいないぞ",
        "MessageKR": "바다에 왔으니 여기서만 할 수 있는 일을 해야지.",
        "MessageTW": "",
        "MessageEN": ""
    },
    {
        "MessageId": 100720060,
        "Flag": 2,
        "Type": 3,
        "NextId": 100720070,
        "MessageType": "Text",
        "ImagePath": "",
        "MessageJP": "海でしか出来ないこと……",
        "MessageKR": "바다에서만 할 수 있는 일이라고 해도……",
        "MessageTW": "",
        "MessageEN": ""
    },
    {
        "MessageId": 100720070,
        "Flag": 2,
        "Type": 3,
        "NextId": 100720080,
        "MessageType": "Text",
        "ImagePath": "",
        "MessageJP": "泳ぐとか？",
        "MessageKR": "해수욕이라도 하자고?",
        "MessageTW": "",
        "MessageEN": ""
    },
    {
        "MessageId": 100720080,
        "Flag": 2,
        "Type": 0,
        "NextId": 100720090,
        "MessageType": "Text",
        "ImagePath": "",
        "MessageJP": "泳ぐだけなら、プールでも良いだろう？",
        "MessageKR": "아니, 바다에서만 할 수 있는 일이라면 따로 있잖아?",
        "MessageTW": "",
        "MessageEN": ""
    },
    {
        "MessageId": 100720090,
        "Flag": 1,
        "Type": 0,
        "NextId": 100720091,
        "MessageType": "Text",
        "ImagePath": "",
        "MessageJP": "つまりだな……",
        "MessageKR": "바로……",
        "MessageTW": "",
        "MessageEN": ""
    },
    {
        "MessageId": 100720091,
        "Flag": 2,
        "Type": 0,
        "NextId": 100710097,
        "MessageType": "Text",
        "ImagePath": "",
        "MessageJP": "海産物を獲りに行くんだ！",
        "MessageKR": "해산물 채취지!",
        "MessageTW": "",
        "MessageEN": ""
    },
    {
        "MessageId": 100710097,
        "Flag": 2,
        "Type": 2,
        "NextId": -1,
        "MessageType": "Text",
        "ImagePath": "",
        "MessageJP": "サキ（水着）の絆イベントへ",
        "MessageKR": "사키(수영복)의 인연스토리로",
        "MessageTW": "前往咲希(泳裝)的羈絆劇情",
        "MessageEN": "Go to Saki (Swimsuit)'s Event"
    }
]