[
    {
        "CharacterId": 10064,
        "MessageJP": "カヨコ（正月）",
        "MessageKR": "카요코(새해)",
        "MessageTW": "佳世子(正月)",
        "MessageEN": "Kayoko (New Year)"
    },
    {
        "MessageId": 100630010,
        "Flag": 2,
        "Type": 4,
        "NextId": 100640010,
        "MessageType": "Text",
        "ImagePath": "",
        "MessageJP": "既読",
        "MessageKR": "읽혔습니다",
        "MessageTW": "已讀",
        "MessageEN": "Message read"
    },
    {
        "MessageId": 100640010,
        "Flag": 2,
        "Type": 0,
        "NextId": 100640020,
        "MessageType": "Text",
        "ImagePath": "",
        "MessageJP": "そろそろ着物を新調しようかな",
        "MessageKR": "그러고 보니 슬슬 새 기모노를 사야 할 것 같네.",
        "MessageTW": "好像差不多該買新和服了",
        "MessageEN": "I've been thinking... I guess it's time to buy a new kimono."
    },
    {
        "MessageId": 100640020,
        "Flag": 1,
        "Type": 0,
        "NextId": 100640030,
        "MessageType": "Text",
        "ImagePath": "",
        "MessageJP": "しばらく買い替えてなかったし",
        "MessageKR": "전에 쓰던 기모노가 너무 낡아서 슬슬 바꿔야 할 것 같아.",
        "MessageTW": "畢竟也好久沒買新的了",
        "MessageEN": "The one I've been wearing is getting too worn out."
    },
    {
        "MessageId": 100640030,
        "Flag": 2,
        "Type": 3,
        "NextId": 100640040,
        "MessageType": "Text",
        "ImagePath": "",
        "MessageJP": "カヨコは自分の着物を持ってるんだね",
        "MessageKR": "카요코는 개인 기모노를 갖고 있었어?",
        "MessageTW": "佳世子有自己的和服阿",
        "MessageEN": "You have your own kimono, Kayoko?"
    },
    {
        "MessageId": 100640040,
        "Flag": 2,
        "Type": 0,
        "NextId": 100640041,
        "MessageType": "Text",
        "ImagePath": "",
        "MessageJP": "うん、そんなに高いものじゃないけど",
        "MessageKR": "응. 그리 비싼 건 아니지만.",
        "MessageTW": "嗯，雖然不是很貴的那種",
        "MessageEN": "Yeah. Not a very fancy one, of course."
    },
    {
        "MessageId": 100640041,
        "Flag": 2,
        "Type": 0,
        "NextId": 100640042,
        "MessageType": "Text",
        "ImagePath": "",
        "MessageJP": "便利屋に入る前は、改まった場所に行くことが多かったから……",
        "MessageKR": "흥신소에 들어오기 전에는 격식 있는 자리에 참가하는 경우가 많아서……",
        "MessageTW": "在加入便利屋之前，常常參加一些注重禮節的場合……",
        "MessageEN": "But before I joined Problem Solver I had to go to a lot of formal events."
    },
    {
        "MessageId": 100640042,
        "Flag": 2,
        "Type": 0,
        "NextId": 100640050,
        "MessageType": "Text",
        "ImagePath": "",
        "MessageJP": "訪問着くらいは持ってたよ",
        "MessageKR": "방문복 정도는 갖고 있었지.",
        "MessageTW": "所以訪問着姑且還是有的",
        "MessageEN": "So it made sense to have my own."
    },
    {
        "MessageId": 100640050,
        "Flag": 2,
        "Type": 3,
        "NextId": 100640060,
        "MessageType": "Text",
        "ImagePath": "",
        "MessageJP": "改まった場所って一体……",
        "MessageKR": "어떤 자리였기에 기모노를……",
        "MessageTW": "注重禮節的場合究竟是……",
        "MessageEN": "What kind of events were these, that you needed a kimono for...?"
    },
    {
        "MessageId": 100640060,
        "Flag": 2,
        "Type": 0,
        "NextId": 100640061,
        "MessageType": "Text",
        "ImagePath": "",
        "MessageJP": "ふふ",
        "MessageKR": "후후",
        "MessageTW": "呵呵",
        "MessageEN": "Heehee."
    },
    {
        "MessageId": 100640061,
        "Flag": 2,
        "Type": 0,
        "NextId": 100630067,
        "MessageType": "Text",
        "ImagePath": "",
        "MessageJP": "機会があれば教えるよ",
        "MessageKR": "나중에 기회가 되면 말해줄게",
        "MessageTW": "有機會再跟你說",
        "MessageEN": "Tell ya later, if I get around to it."
    },
    {
        "MessageId": 100630067,
        "Flag": 2,
        "Type": 2,
        "NextId": -1,
        "MessageType": "Text",
        "ImagePath": "",
        "MessageJP": "カヨコ（正月）の絆イベントへ",
        "MessageKR": "카요코(새해)의 인연스토리로",
        "MessageTW": "前往佳世子(正月)的羈絆劇情",
        "MessageEN": "Go to Kayoko (New Year)'s Event"
    }
]