[
    {
        "CharacterId": 20019,
        "MessageJP": "アカネ（バニーガール）",
        "MessageKR": "아카네(바니걸)",
        "MessageTW": "朱音(兔女郎)",
        "MessageEN": "Akane (Bunny)"
    },
    {
        "MessageId": 200180090,
        "Flag": 2,
        "Type": 4,
        "NextId": 200190090,
        "MessageType": "Text",
        "ImagePath": "",
        "MessageJP": "既読",
        "MessageKR": "읽혔습니다",
        "MessageTW": "已讀",
        "MessageEN": "Message read"
    },
    {
        "MessageId": 200190090,
        "Flag": 2,
        "Type": 0,
        "NextId": 200190100,
        "MessageType": "Text",
        "ImagePath": "",
        "MessageJP": "先日は大変失礼いたしました",
        "MessageKR": "예전에는 너무 실례가 많았어요.",
        "MessageTW": "之前真是非常失禮",
        "MessageEN": "I was a bit rude earlier..."
    },
    {
        "MessageId": 200190100,
        "Flag": 1,
        "Type": 0,
        "NextId": 200190101,
        "MessageType": "Text",
        "ImagePath": "",
        "MessageJP": "心が逸るあまり、ご無礼を働いてしまいました",
        "MessageKR": "마음이 앞선 나머지 무례를 저질렀네요.",
        "MessageTW": "因為太過慌張而做出了無禮的舉動",
        "MessageEN": "I got ahead of myself..."
    },
    {
        "MessageId": 200190101,
        "Flag": 2,
        "Type": 0,
        "NextId": 200190110,
        "MessageType": "Text",
        "ImagePath": "",
        "MessageJP": "申し訳ございません",
        "MessageKR": "죄송합니다.",
        "MessageTW": "非常對不起",
        "MessageEN": "I'd like to apologize."
    },
    {
        "MessageId": 200190110,
        "Flag": 2,
        "Type": 3,
        "NextId": 200190120,
        "MessageType": "Text",
        "ImagePath": "",
        "MessageJP": "いや……私こそごめんね",
        "MessageKR": "아냐…… 나야 말로 경우가 없었지.",
        "MessageTW": "不……該道歉的是我",
        "MessageEN": "No, no. You did nothing wrong."
    },
    {
        "MessageId": 200190110,
        "Flag": 2,
        "Type": 3,
        "NextId": 200190120,
        "MessageType": "Text",
        "ImagePath": "",
        "MessageJP": "むしろ感謝の気持ちでいっぱいです！",
        "MessageKR": "오히려 감사드리고 싶을 정도입니다!",
        "MessageTW": "不如該說非常感謝！",
        "MessageEN": "If anything, I should be thanking you!"
    },
    {
        "MessageId": 200190120,
        "Flag": 2,
        "Type": 0,
        "NextId": 200190121,
        "MessageType": "Text",
        "ImagePath": "",
        "MessageJP": "またご奉仕させていただけませんか？",
        "MessageKR": "다음에…… 다시 봉사를 허락해 주실 수 있으신가요?",
        "MessageTW": "還能讓我再服務您嗎？",
        "MessageEN": "...Would you please let me serve you again?"
    },
    {
        "MessageId": 200190121,
        "Flag": 2,
        "Type": 0,
        "NextId": 200190130,
        "MessageType": "Text",
        "ImagePath": "",
        "MessageJP": "お互い気持ちを落ち着かせて……二人だけの時間で",
        "MessageKR": "찬찬히 시간을 들인…… 둘만의 봉사를요.",
        "MessageTW": "在彼此都冷靜的……只屬於我們兩個人的時間",
        "MessageEN": "I'll provide a special, personal service. No limits."
    },
    {
        "MessageId": 200190130,
        "Flag": 2,
        "Type": 3,
        "NextId": 200190140,
        "MessageType": "Text",
        "ImagePath": "",
        "MessageJP": "た、他意はないよね？",
        "MessageKR": "정말로 다른 뜻 없는 거 맞지?!",
        "MessageTW": "沒，沒有其他意思吧？",
        "MessageEN": "You don't have any ulterior motives, do you?!"
    },
    {
        "MessageId": 200190130,
        "Flag": 2,
        "Type": 3,
        "NextId": 200190150,
        "MessageType": "Text",
        "ImagePath": "",
        "MessageJP": "ぜひお願いします！",
        "MessageKR": "오히려 이쪽에서 부탁드리고 싶은데요!",
        "MessageTW": "請務必這麼做！",
        "MessageEN": "Honestly, I should have asked that first!"
    },
    {
        "MessageId": 200190140,
        "Flag": 2,
        "Type": 0,
        "NextId": 200190160,
        "MessageType": "Text",
        "ImagePath": "",
        "MessageJP": "ええと……それは、どういう意味でしょうか？",
        "MessageKR": "네? 무슨 의미세요?",
        "MessageTW": "呃……那是什麼意思呢？",
        "MessageEN": "Hm? What could you possibly mean?"
    },
    {
        "MessageId": 200190150,
        "Flag": 1,
        "Type": 0,
        "NextId": 200180167,
        "MessageType": "Text",
        "ImagePath": "",
        "MessageJP": "安心しました……お待ちしておりますね",
        "MessageKR": "안심했습니다…… 기다리고 있을게요.",
        "MessageTW": "那我就放心了……我等著您哦",
        "MessageEN": "Well... I feel a bit better. I'll be waiting for you!"
    },
    {
        "MessageId": 200180167,
        "Flag": 2,
        "Type": 2,
        "NextId": 200190160,
        "MessageType": "Text",
        "ImagePath": "",
        "MessageJP": "アカネ（バニーガール）の絆イベントへ",
        "MessageKR": "아카네(바니걸)의 인연스토리로",
        "MessageTW": "前往朱音(兔女郎)的羈絆劇情",
        "MessageEN": "Go to Akane (Bunny)'s Event"
    },
    {
        "MessageId": 200190160,
        "Flag": 2,
        "Type": 0,
        "NextId": 200190170,
        "MessageType": "Text",
        "ImagePath": "",
        "MessageJP": "ゆっくり眠れましたか、ご主人様？",
        "MessageKR": "편히 주무셨나요, 주인님?",
        "MessageTW": "睡得好嗎，主人？",
        "MessageEN": "Did you sleep well, Master?"
    },
    {
        "MessageId": 200190170,
        "Flag": 2,
        "Type": 3,
        "NextId": 200190180,
        "MessageType": "Text",
        "ImagePath": "",
        "MessageJP": "おかげで熟睡できたよ",
        "MessageKR": "덕분에 푹 잘 수 있었어.",
        "MessageTW": "託你的福，我睡得很好",
        "MessageEN": "Like a baby, thanks to you."
    },
    {
        "MessageId": 200190180,
        "Flag": 2,
        "Type": 0,
        "NextId": 200190190,
        "MessageType": "Text",
        "ImagePath": "",
        "MessageJP": "良かったです",
        "MessageKR": "다행이에요.",
        "MessageTW": "太好了",
        "MessageEN": "What a relief."
    },
    {
        "MessageId": 200190190,
        "Flag": 1,
        "Type": 0,
        "NextId": 200190191,
        "MessageType": "Text",
        "ImagePath": "",
        "MessageJP": "実は、あの茶葉には……",
        "MessageKR": "사실 그때 드린 차에는,",
        "MessageTW": "其實，那個茶葉……",
        "MessageEN": "The tea I made for you..."
    },
    {
        "MessageId": 200190191,
        "Flag": 2,
        "Type": 0,
        "NextId": 200190200,
        "MessageType": "Text",
        "ImagePath": "",
        "MessageJP": "睡眠の質が良くなるリラックス効果があるそうで……",
        "MessageKR": "수면의 질이 좋아지는 릴렉스 효과가 있다고 해요……",
        "MessageTW": "似乎有能提高睡眠品質的放鬆效果……",
        "MessageEN": "It's meant to help you relax and sleep well."
    },
    {
        "MessageId": 200190200,
        "Flag": 1,
        "Type": 0,
        "NextId": 200190210,
        "MessageType": "Text",
        "ImagePath": "",
        "MessageJP": "少しでもお疲れが取れたのなら、淹れた甲斐がありました",
        "MessageKR": "조금이라도 피로가 풀리셨다면, 차를 내린 보람이 있네요.",
        "MessageTW": "多少能消除一些疲憊的話，我泡的茶也有意義了",
        "MessageEN": "I'm relieved it worked!"
    },
    {
        "MessageId": 200190210,
        "Flag": 2,
        "Type": 3,
        "NextId": 200190220,
        "MessageType": "Text",
        "ImagePath": "",
        "MessageJP": "そうだったんだね。ありがとう",
        "MessageKR": "그랬구나. 고마워.",
        "MessageTW": "原來是這樣啊，謝謝",
        "MessageEN": "No wonder I got so drowsy! Thank you."
    },
    {
        "MessageId": 200190220,
        "Flag": 2,
        "Type": 0,
        "NextId": 200190221,
        "MessageType": "Text",
        "ImagePath": "",
        "MessageJP": "うれしいお言葉です",
        "MessageKR": "별말씀을요.",
        "MessageTW": "您的話真令人開心",
        "MessageEN": "Of course, Sensei."
    },
    {
        "MessageId": 200190221,
        "Flag": 2,
        "Type": 0,
        "NextId": 200190230,
        "MessageType": "Text",
        "ImagePath": "",
        "MessageJP": "ご主人様の幸せが、私の幸せですから",
        "MessageKR": "주인님의 행복이, 저의 행복이랍니다.",
        "MessageTW": "主人的幸福，就是我的幸福",
        "MessageEN": "I'm elated I could be of use."
    },
    {
        "MessageId": 200190230,
        "Flag": 2,
        "Type": 3,
        "NextId": 200190240,
        "MessageType": "Text",
        "ImagePath": "",
        "MessageJP": "ところで、アカネはシャーレまで何か用事があったの？",
        "MessageKR": "그런데 아카네는 샬레까지 와서, 무슨 볼일이 있었던 거야?",
        "MessageTW": "話說回來，朱音來到夏萊有什麼事嗎？",
        "MessageEN": "By the way, what brought you to Schale? Errands?"
    },
    {
        "MessageId": 200190240,
        "Flag": 2,
        "Type": 3,
        "NextId": 200190250,
        "MessageType": "Text",
        "ImagePath": "",
        "MessageJP": "それとも掃除のため？",
        "MessageKR": "아니면 청소를 위해서 온 건가?",
        "MessageTW": "還是是來打掃的呢？",
        "MessageEN": "Cleaning?"
    },
    {
        "MessageId": 200190250,
        "Flag": 2,
        "Type": 0,
        "NextId": 200190251,
        "MessageType": "Text",
        "ImagePath": "",
        "MessageJP": "どうでしょう？",
        "MessageKR": "글쎄요?",
        "MessageTW": "是為什麼呢？",
        "MessageEN": "Well..."
    },
    {
        "MessageId": 200190251,
        "Flag": 2,
        "Type": 0,
        "NextId": 200190260,
        "MessageType": "Text",
        "ImagePath": "",
        "MessageJP": "眠っているご主人様の顔が見られて",
        "MessageKR": "잠든 주인님의 얼굴을 볼 수 있어서,",
        "MessageTW": "能看到主人的睡臉",
        "MessageEN": "Let's just say..."
    },
    {
        "MessageId": 200190260,
        "Flag": 1,
        "Type": 0,
        "NextId": 200190270,
        "MessageType": "Text",
        "ImagePath": "",
        "MessageJP": "幸運でした、とだけ申し上げます",
        "MessageKR": "행운이었다고만 말씀드릴게요.",
        "MessageTW": "真是幸運，僅此而已",
        "MessageEN": "I was very lucky to catch you sleeping."
    },
    {
        "MessageId": 200190270,
        "Flag": 1,
        "Type": 0,
        "NextId": -1,
        "MessageType": "Text",
        "ImagePath": "",
        "MessageJP": "ぴょんぴょん",
        "MessageKR": "뿅뿅.",
        "MessageTW": "蹦蹦",
        "MessageEN": "Boing, boing."
    }
]