[
    {
        "CharacterId": 10024,
        "MessageJP": "シロコ（ライディング）",
        "MessageKR": "시로코(라이딩)",
        "MessageTW": "白子(單車)",
        "MessageEN": "Shiroko (Cycling)"
    },
    {
        "MessageId": 100230110,
        "Flag": 2,
        "Type": 4,
        "NextId": 100240110,
        "MessageType": "Text",
        "ImagePath": "",
        "MessageJP": "既読",
        "MessageKR": "읽혔습니다",
        "MessageTW": "已讀",
        "MessageEN": "Message read"
    },
    {
        "MessageId": 100240110,
        "Flag": 2,
        "Type": 0,
        "NextId": 100240120,
        "MessageType": "Text",
        "ImagePath": "",
        "MessageJP": "先生",
        "MessageKR": "선생님. 연락이야.",
        "MessageTW": "老師",
        "MessageEN": "How are you, Sensei?"
    },
    {
        "MessageId": 100240120,
        "Flag": 1,
        "Type": 0,
        "NextId": 100240130,
        "MessageType": "Text",
        "ImagePath": "",
        "MessageJP": "今アビドスを完全に抜けたところ、もうすぐ海岸道路に着きそう",
        "MessageKR": "아비도스를 완전히 빠져나왔어. 곧 있으면 해안 도로에 도착할 거야.",
        "MessageTW": "現在已經完全離開阿拜多斯，馬上就要到海岸道路了",
        "MessageEN": "I'm outside of Abydos now. I should reach the coastal road soon."
    },
    {
        "MessageId": 100240130,
        "Flag": 2,
        "Type": 3,
        "NextId": 100240140,
        "MessageType": "Text",
        "ImagePath": "",
        "MessageJP": "速いね……！？",
        "MessageKR": "벌써 거기까지? 대단한걸.",
        "MessageTW": "真快呢……！？",
        "MessageEN": "That far already? That's amazing."
    },
    {
        "MessageId": 100240130,
        "Flag": 2,
        "Type": 3,
        "NextId": 100240140,
        "MessageType": "Text",
        "ImagePath": "",
        "MessageJP": "プロ選手みたいな速度だね……今のところ順調？",
        "MessageKR": "전문가 같아.",
        "MessageTW": "像職業選手一樣的速度呢……目前為止還順利嗎？",
        "MessageEN": "Like a professional, I should say."
    },
    {
        "MessageId": 100240140,
        "Flag": 2,
        "Type": 0,
        "NextId": 100240141,
        "MessageType": "Text",
        "ImagePath": "",
        "MessageJP": "ん",
        "MessageKR": "어……",
        "MessageTW": "嗯",
        "MessageEN": "Uhhh..."
    },
    {
        "MessageId": 100240141,
        "Flag": 2,
        "Type": 0,
        "NextId": 100240150,
        "MessageType": "Text",
        "ImagePath": "",
        "MessageJP": "あ、そういえば……",
        "MessageKR": "음……",
        "MessageTW": "啊，話說回來……",
        "MessageEN": "Um..."
    },
    {
        "MessageId": 100240150,
        "Flag": 2,
        "Type": 3,
        "NextId": 100240160,
        "MessageType": "Text",
        "ImagePath": "",
        "MessageJP": "どうしたの？",
        "MessageKR": "시로코?",
        "MessageTW": "怎麼了？",
        "MessageEN": "Shiroko?"
    },
    {
        "MessageId": 100240160,
        "Flag": 2,
        "Type": 0,
        "NextId": 100240170,
        "MessageType": "Text",
        "ImagePath": "",
        "MessageJP": "あ、いや",
        "MessageKR": "아니.",
        "MessageTW": "啊，不",
        "MessageEN": "No."
    },
    {
        "MessageId": 100240170,
        "Flag": 1,
        "Type": 0,
        "NextId": 100240171,
        "MessageType": "Text",
        "ImagePath": "",
        "MessageJP": "ごめん、やっぱり大丈夫",
        "MessageKR": "응.",
        "MessageTW": "抱歉，還是算了",
        "MessageEN": "Yes."
    },
    {
        "MessageId": 100240171,
        "Flag": 2,
        "Type": 0,
        "NextId": 100240180,
        "MessageType": "Text",
        "ImagePath": "",
        "MessageJP": "ありがとう",
        "MessageKR": "고마워.",
        "MessageTW": "謝謝",
        "MessageEN": "Thanks."
    },
    {
        "MessageId": 100240180,
        "Flag": 1,
        "Type": 0,
        "NextId": 100240181,
        "MessageType": "Text",
        "ImagePath": "",
        "MessageJP": "この後は、海岸道路沿いにずっと走るつもり",
        "MessageKR": "다음엔 해안도로 중간까지 쭉 달릴 거야.",
        "MessageTW": "接下來，我打算沿著海岸道路一直騎",
        "MessageEN": "Then I'll head straight for the coastal road."
    },
    {
        "MessageId": 100240181,
        "Flag": 2,
        "Type": 0,
        "NextId": 100230197,
        "MessageType": "Text",
        "ImagePath": "",
        "MessageJP": "じゃあまた連絡するね、先生",
        "MessageKR": "그럼 그때 다시 연락할게. 선생님.",
        "MessageTW": "那麼再聯絡吧，老師",
        "MessageEN": "I'll message you there, Sensei."
    },
    {
        "MessageId": 100230197,
        "Flag": 2,
        "Type": 2,
        "NextId": 100240190,
        "MessageType": "Text",
        "ImagePath": "",
        "MessageJP": "シロコ（ライディング）の絆イベントへ",
        "MessageKR": "시로코(라이딩)의 인연스토리로",
        "MessageTW": "前往白子(單車)的羈絆劇情",
        "MessageEN": "Go to Shiroko (Cycling)'s Event"
    },
    {
        "MessageId": 100240190,
        "Flag": 2,
        "Type": 0,
        "NextId": 100240191,
        "MessageType": "Text",
        "ImagePath": "",
        "MessageJP": "ありがとう、先生。色々と助かった",
        "MessageKR": "덕분에 계속해서 달릴 수 있었어.",
        "MessageTW": "謝謝老師幫我這麼多",
        "MessageEN": "I was able to stay on the move thanks to you."
    },
    {
        "MessageId": 100240191,
        "Flag": 2,
        "Type": 0,
        "NextId": 100240200,
        "MessageType": "Text",
        "ImagePath": "",
        "MessageJP": "カバンの中に入れてると、どうしても飲み物はぬるくなっちゃうし",
        "MessageKR": "역시 가방 안에 든 것들은 시간이 지나면서 조금씩 식으니까.",
        "MessageTW": "飲料放在背包裡總是會變溫的",
        "MessageEN": "Since the stuff in my bag heats up after a while"
    },
    {
        "MessageId": 100240200,
        "Flag": 1,
        "Type": 0,
        "NextId": 100240201,
        "MessageType": "Text",
        "ImagePath": "",
        "MessageJP": "持ってきてくれたドリンク、すっごく冷たくて嬉しかった",
        "MessageKR": "막 챙겨 온 드링크가 훨씬 시원한 것 같아.",
        "MessageTW": "老師幫我帶來的飲料非常冰涼，我很開心",
        "MessageEN": "The drink I just got is cooler than those."
    },
    {
        "MessageId": 100240201,
        "Flag": 2,
        "Type": 0,
        "NextId": 100240210,
        "MessageType": "Text",
        "ImagePath": "",
        "MessageJP": "タオルも",
        "MessageKR": "타올도",
        "MessageTW": "毛巾也是",
        "MessageEN": "And the towels"
    },
    {
        "MessageId": 100240210,
        "Flag": 1,
        "Type": 0,
        "NextId": 100240211,
        "MessageType": "Text",
        "ImagePath": "",
        "MessageJP": "あ",
        "MessageKR": "……아.",
        "MessageTW": "啊",
        "MessageEN": "Oh."
    },
    {
        "MessageId": 100240211,
        "Flag": 2,
        "Type": 0,
        "NextId": 100240220,
        "MessageType": "Text",
        "ImagePath": "",
        "MessageJP": "そういえばさっき先生に渡したタオル、良ければ……",
        "MessageKR": "그러고 보니 나에게서 받아 간 타올은 어떻게 됐어?",
        "MessageTW": "這麼說來，剛才給老師的毛巾，如果可以的話……",
        "MessageEN": "What happened to the towel I gave you before?"
    },
    {
        "MessageId": 100240220,
        "Flag": 2,
        "Type": 3,
        "NextId": 100240230,
        "MessageType": "Text",
        "ImagePath": "",
        "MessageJP": "洗濯してちゃんと保管しておいたよ。今度返すね",
        "MessageKR": "세탁해서 잘 보관해뒀어.",
        "MessageTW": "已經洗好收起來了。下次再還給你",
        "MessageEN": "I washed it and put it away."
    },
    {
        "MessageId": 100240230,
        "Flag": 2,
        "Type": 0,
        "NextId": 100240231,
        "MessageType": "Text",
        "ImagePath": "",
        "MessageJP": "えっと",
        "MessageKR": "……아,",
        "MessageTW": "那個",
        "MessageEN": "Ah"
    },
    {
        "MessageId": 100240231,
        "Flag": 2,
        "Type": 0,
        "NextId": 100240240,
        "MessageType": "Text",
        "ImagePath": "",
        "MessageJP": "うん、やっぱりそうだよね……",
        "MessageKR": "응…….",
        "MessageTW": "嗯，果然是這樣啊……",
        "MessageEN": "Yes..."
    },
    {
        "MessageId": 100240240,
        "Flag": 1,
        "Type": 0,
        "NextId": 100240241,
        "MessageType": "Text",
        "ImagePath": "",
        "MessageJP": "ううん、ありがとう",
        "MessageKR": "역시 그렇겠지. 고마워.",
        "MessageTW": "沒事，謝謝",
        "MessageEN": "I see. Thanks."
    },
    {
        "MessageId": 100240241,
        "Flag": 2,
        "Type": 0,
        "NextId": 100240242,
        "MessageType": "Text",
        "ImagePath": "",
        "MessageJP": "んと",
        "MessageKR": "아무튼",
        "MessageTW": "然後",
        "MessageEN": "Anyway"
    },
    {
        "MessageId": 100240242,
        "Flag": 2,
        "Type": 0,
        "NextId": 100240250,
        "MessageType": "Text",
        "ImagePath": "",
        "MessageJP": "じゃあ",
        "MessageKR": "다음에 또 연락할게. 선생님.",
        "MessageTW": "那就",
        "MessageEN": "I'll talk to you next time, Sensei."
    },
    {
        "MessageId": 100240250,
        "Flag": 1,
        "Type": 0,
        "NextId": -1,
        "MessageType": "Text",
        "ImagePath": "",
        "MessageJP": "また連絡するね、先生",
        "MessageKR": "그럼.",
        "MessageTW": "下次再連絡，老師",
        "MessageEN": "Until we meet again."
    }
]