[
    {
        "CharacterId": 16013,
        "MessageJP": "コハル（水着）",
        "MessageKR": "코하루(수영복)",
        "MessageTW": "コハル（水着）",
        "MessageEN": "Koharu (Swimsuit)"
    },
    {
        "MessageId": 160120120,
        "Flag": 2,
        "Type": 4,
        "NextId": 160130120,
        "MessageType": "Text",
        "ImagePath": "",
        "MessageJP": "既読",
        "MessageKR": "읽혔습니다",
        "MessageTW": "已讀",
        "MessageEN": "Message read"
    },
    {
        "MessageId": 160130120,
        "Flag": 2,
        "Type": 0,
        "NextId": 160130130,
        "MessageType": "Text",
        "ImagePath": "",
        "MessageJP": "先生",
        "MessageKR": "선생님",
        "MessageTW": "",
        "MessageEN": ""
    },
    {
        "MessageId": 160130130,
        "Flag": 1,
        "Type": 0,
        "NextId": 160130131,
        "MessageType": "Text",
        "ImagePath": "",
        "MessageJP": "今度はどこにいるの？",
        "MessageKR": "지금 어디야?",
        "MessageTW": "",
        "MessageEN": ""
    },
    {
        "MessageId": 160130131,
        "Flag": 2,
        "Type": 0,
        "NextId": 160130140,
        "MessageType": "Text",
        "ImagePath": "",
        "MessageJP": "あ、いや……それよりも",
        "MessageKR": "아니아니, 그건 중요하지 않지",
        "MessageTW": "",
        "MessageEN": ""
    },
    {
        "MessageId": 160130140,
        "Flag": 1,
        "Type": 0,
        "NextId": 160130141,
        "MessageType": "Text",
        "ImagePath": "",
        "MessageJP": "こっちに来て！",
        "MessageKR": "지금 이쪽으로 와 봐!",
        "MessageTW": "",
        "MessageEN": ""
    },
    {
        "MessageId": 160130141,
        "Flag": 2,
        "Type": 0,
        "NextId": 160130150,
        "MessageType": "Text",
        "ImagePath": "",
        "MessageJP": "今すぐ！！",
        "MessageKR": "빨리!!",
        "MessageTW": "",
        "MessageEN": ""
    },
    {
        "MessageId": 160130150,
        "Flag": 2,
        "Type": 3,
        "NextId": 160130160,
        "MessageType": "Text",
        "ImagePath": "",
        "MessageJP": "コハル？",
        "MessageKR": "코하루?",
        "MessageTW": "",
        "MessageEN": ""
    },
    {
        "MessageId": 160130150,
        "Flag": 2,
        "Type": 3,
        "NextId": 160130160,
        "MessageType": "Text",
        "ImagePath": "",
        "MessageJP": "どうしたの？",
        "MessageKR": "무슨 일이야?",
        "MessageTW": "",
        "MessageEN": ""
    },
    {
        "MessageId": 160130160,
        "Flag": 2,
        "Type": 0,
        "NextId": 160130161,
        "MessageType": "Text",
        "ImagePath": "",
        "MessageJP": "説明はあと！",
        "MessageKR": "설명은 나중에",
        "MessageTW": "",
        "MessageEN": ""
    },
    {
        "MessageId": 160130161,
        "Flag": 2,
        "Type": 0,
        "NextId": 160130170,
        "MessageType": "Text",
        "ImagePath": "",
        "MessageJP": "場所はいま送るから",
        "MessageKR": "장소는 내가 보내줄 테니까",
        "MessageTW": "",
        "MessageEN": ""
    },
    {
        "MessageId": 160130170,
        "Flag": 1,
        "Type": 0,
        "NextId": 160130171,
        "MessageType": "Text",
        "ImagePath": "",
        "MessageJP": "早く！",
        "MessageKR": "빨리",
        "MessageTW": "",
        "MessageEN": ""
    },
    {
        "MessageId": 160130171,
        "Flag": 2,
        "Type": 0,
        "NextId": 160120187,
        "MessageType": "Text",
        "ImagePath": "",
        "MessageJP": "急いで！！！",
        "MessageKR": "빨리!!!!",
        "MessageTW": "",
        "MessageEN": ""
    },
    {
        "MessageId": 160120187,
        "Flag": 2,
        "Type": 2,
        "NextId": 160130180,
        "MessageType": "Text",
        "ImagePath": "",
        "MessageJP": "コハル（水着）の絆イベントへ",
        "MessageKR": "코하루(수영복)의 인연스토리로",
        "MessageTW": "前往コハル（水着）的羈絆劇情",
        "MessageEN": "Go to Koharu (Swimsuit)'s Event"
    },
    {
        "MessageId": 160130180,
        "Flag": 2,
        "Type": 0,
        "NextId": 160130190,
        "MessageType": "Text",
        "ImagePath": "",
        "MessageJP": "先生\u200b",
        "MessageKR": "선생님\u200b",
        "MessageTW": "",
        "MessageEN": ""
    },
    {
        "MessageId": 160130190,
        "Flag": 1,
        "Type": 0,
        "NextId": 160130200,
        "MessageType": "Text",
        "ImagePath": "",
        "MessageJP": "今日のことは誰にも言わないで",
        "MessageKR": "오늘 일은 아무한테도 이야기하지 마",
        "MessageTW": "",
        "MessageEN": ""
    },
    {
        "MessageId": 160130200,
        "Flag": 1,
        "Type": 0,
        "NextId": 160130201,
        "MessageType": "Text",
        "ImagePath": "",
        "MessageJP": "特に、その……",
        "MessageKR": "특히 내가 그",
        "MessageTW": "",
        "MessageEN": ""
    },
    {
        "MessageId": 160130201,
        "Flag": 2,
        "Type": 0,
        "NextId": 160130210,
        "MessageType": "Text",
        "ImagePath": "",
        "MessageJP": "私が泣いちゃったのとか",
        "MessageKR": "울었다던가",
        "MessageTW": "",
        "MessageEN": ""
    },
    {
        "MessageId": 160130210,
        "Flag": 1,
        "Type": 0,
        "NextId": 160130211,
        "MessageType": "Text",
        "ImagePath": "",
        "MessageJP": "絶対、絶対に言ったらダメだからね？",
        "MessageKR": "아무튼 절대 그런 이야기 하면 안 돼. 알았지!?",
        "MessageTW": "",
        "MessageEN": ""
    },
    {
        "MessageId": 160130211,
        "Flag": 2,
        "Type": 0,
        "NextId": 160130220,
        "MessageType": "Text",
        "ImagePath": "",
        "MessageJP": "分かった？もし言ったら死刑よ！",
        "MessageKR": "사형이야!",
        "MessageTW": "",
        "MessageEN": ""
    },
    {
        "MessageId": 160130220,
        "Flag": 1,
        "Type": 0,
        "NextId": -1,
        "MessageType": "Text",
        "ImagePath": "",
        "MessageJP": "本当に死刑なんだから！！！",
        "MessageKR": "진짜 사형이니까!!",
        "MessageTW": "",
        "MessageEN": ""
    }
]